lagrange/__init__.py
lagrange/lagrange_client.py
lagrange/api/__init__.py
lagrange/api/dataset.py
lagrange/common/__init__.py
lagrange/common/dataset.py
lagrange/core/__init__.py
lagrange/docs/__init__.py
tests/__init__.py
tests/test_datasets.py
lagrange_python_client-0.1.2.dist-info/LICENCE
lagrange_python_client-0.1.2.dist-info/METADATA
lagrange_python_client-0.1.2.dist-info/WHEEL
lagrange_python_client-0.1.2.dist-info/top_level.txt
lagrange_python_client-0.1.2.dist-info/RECORD
