Metadata-Version: 2.1
Name: lagrange-python-client
Version: 0.1.2
Summary: Useful tools to work with Lagrange DAO in Python
Home-page: https://github.com/lagrangedao/lagrange-python-client
Download-URL: https://pypi.org/project/lagrange-python-client
Author: Charles Cao
Author-email: datadaoswan@gmail.com
License: MIT
Keywords: LagrangeDao,Deeplearning,Cloud
License-File: LICENCE
